hipercow/__about__.py
hipercow/__init__.py
hipercow/bundle.py
hipercow/cli.py
hipercow/configure.py
hipercow/driver.py
hipercow/environment.py
hipercow/example.py
hipercow/provision.py
hipercow/py.typed
hipercow/resources.py
hipercow/root.py
hipercow/task.py
hipercow/task_create.py
hipercow/task_create_bulk.py
hipercow/task_eval.py
hipercow/ui.py
hipercow/util.py
hipercow/dide/auth.py
hipercow/dide/batch_linux.py
hipercow/dide/batch_windows.py
hipercow/dide/bootstrap.py
hipercow/dide/bootstrap_linux.py
hipercow/dide/bootstrap_windows.py
hipercow/dide/check.py
hipercow/dide/configuration.py
hipercow/dide/driver.py
hipercow/dide/mounts.py
hipercow/dide/provision.py
hipercow/dide/web.py
hipercow/environment_engines/__init__.py
hipercow/environment_engines/base.py
hipercow/environment_engines/empty.py
hipercow/environment_engines/pip.py
hipercow-0.2.2.dist-info/METADATA
hipercow-0.2.2.dist-info/WHEEL
hipercow-0.2.2.dist-info/entry_points.txt
hipercow-0.2.2.dist-info/licenses/LICENSE.txt
hipercow-0.2.2.dist-info/RECORD
